prompt_importer/__init__.py
prompt_importer/importer.py
prompt_importer-0.2.1.dist-info/LICENSE.txt
prompt_importer-0.2.1.dist-info/WHEEL
prompt_importer-0.2.1.dist-info/METADATA
prompt_importer-0.2.1.dist-info/RECORD
