Metadata-Version: 2.1
Name: prompt-importer
Version: 0.2.1
Summary: A base class for building prompt-based beancount importers
Home-page: https://github.com/heldridge/prompt_importer
License: GPL-3.0-only
Author: Harry Eldridge
Author-email: eldridgemharry@gmail.com
Requires-Python: >=3.10,<4.0
Classifier: License :: OSI Approved :: GNU General Public License v3 (GPLv3)
Classifier: Programming Language :: Python :: 3
Classifier: Programming Language :: Python :: 3.10
Requires-Dist: beancount (>=2.3.5,<3.0.0)
Requires-Dist: blessed (>=1.19.1,<2.0.0)
Project-URL: Repository, https://github.com/heldridge/prompt_importer
